main.py
dbsm-0.0.1.dist-info/METADATA
dbsm-0.0.1.dist-info/WHEEL
dbsm-0.0.1.dist-info/top_level.txt
dbsm-0.0.1.dist-info/RECORD
