Metadata-Version: 2.1
Name: dbsm
Version: 0.0.1
Summary: dbsm
Author: 4sushi
License: MIT
Keywords: dbsm
Platform: UNKNOWN
Classifier: Programming Language :: Python :: 3
Classifier: License :: OSI Approved :: MIT License
Classifier: Operating System :: OS Independent
Requires-Python: >=3.7
